{"avg_ep_ret": -50.772433155133356, "avg_ep_len": 999.0, "timesteps": 4800}
{"avg_ep_ret": -50.53980624237627, "avg_ep_len": 999.0, "timesteps": 9600}
{"avg_ep_ret": -50.269479080645404, "avg_ep_len": 999.0, "timesteps": 14400}
{"avg_ep_ret": -51.145015713822644, "avg_ep_len": 999.0, "timesteps": 19200}
{"avg_ep_ret": -50.57178424706555, "avg_ep_len": 999.0, "timesteps": 24000}
{"avg_ep_ret": -50.62122154589442, "avg_ep_len": 999.0, "timesteps": 28800}
{"avg_ep_ret": -50.42020917846392, "avg_ep_len": 999.0, "timesteps": 33600}
{"avg_ep_ret": -50.120613492485134, "avg_ep_len": 999.0, "timesteps": 38400}
{"avg_ep_ret": -50.69563820949678, "avg_ep_len": 999.0, "timesteps": 43200}
{"avg_ep_ret": -50.51083784828711, "avg_ep_len": 999.0, "timesteps": 48000}
{"avg_ep_ret": -50.897950766072576, "avg_ep_len": 999.0, "timesteps": 52800}
{"avg_ep_ret": -50.06780706380963, "avg_ep_len": 999.0, "timesteps": 57600}
{"avg_ep_ret": -49.68705870932443, "avg_ep_len": 999.0, "timesteps": 62400}
{"avg_ep_ret": -50.15340703033465, "avg_ep_len": 999.0, "timesteps": 67200}
{"avg_ep_ret": -50.35438265181133, "avg_ep_len": 999.0, "timesteps": 72000}
{"avg_ep_ret": -51.03222294213726, "avg_ep_len": 999.0, "timesteps": 76800}
{"avg_ep_ret": -50.7632578583856, "avg_ep_len": 999.0, "timesteps": 81600}
{"avg_ep_ret": -49.833924925613594, "avg_ep_len": 999.0, "timesteps": 86400}
{"avg_ep_ret": -50.05290725471076, "avg_ep_len": 999.0, "timesteps": 91200}
{"avg_ep_ret": -50.63263401481, "avg_ep_len": 999.0, "timesteps": 96000}
{"avg_ep_ret": -50.77791460066665, "avg_ep_len": 999.0, "timesteps": 100800}
{"avg_ep_ret": -50.13587649691037, "avg_ep_len": 999.0, "timesteps": 105600}
{"avg_ep_ret": -50.59951068146501, "avg_ep_len": 999.0, "timesteps": 110400}
{"avg_ep_ret": -49.899516096844515, "avg_ep_len": 999.0, "timesteps": 115200}
{"avg_ep_ret": -50.77322769892598, "avg_ep_len": 999.0, "timesteps": 120000}
{"avg_ep_ret": -50.45749018635911, "avg_ep_len": 999.0, "timesteps": 124800}
{"avg_ep_ret": -50.67182256908818, "avg_ep_len": 999.0, "timesteps": 129600}
{"avg_ep_ret": -50.1644995831859, "avg_ep_len": 999.0, "timesteps": 134400}
{"avg_ep_ret": -51.096598217660684, "avg_ep_len": 999.0, "timesteps": 139200}
{"avg_ep_ret": -50.169255883406144, "avg_ep_len": 999.0, "timesteps": 144000}
{"avg_ep_ret": -50.92240642214779, "avg_ep_len": 999.0, "timesteps": 148800}
{"avg_ep_ret": -50.00230597199989, "avg_ep_len": 999.0, "timesteps": 153600}
{"avg_ep_ret": -51.05175660830533, "avg_ep_len": 999.0, "timesteps": 158400}
{"avg_ep_ret": -49.935657065218884, "avg_ep_len": 999.0, "timesteps": 163200}
{"avg_ep_ret": -50.48842888938724, "avg_ep_len": 999.0, "timesteps": 168000}
{"avg_ep_ret": -50.521017304328616, "avg_ep_len": 999.0, "timesteps": 172800}
{"avg_ep_ret": -50.0473084227509, "avg_ep_len": 999.0, "timesteps": 177600}
{"avg_ep_ret": -50.23518565822478, "avg_ep_len": 999.0, "timesteps": 182400}
{"avg_ep_ret": -50.14348142409773, "avg_ep_len": 999.0, "timesteps": 187200}
{"avg_ep_ret": -49.875788912808744, "avg_ep_len": 999.0, "timesteps": 192000}
{"avg_ep_ret": -51.147215127805445, "avg_ep_len": 999.0, "timesteps": 196800}
{"avg_ep_ret": -49.85004555623643, "avg_ep_len": 999.0, "timesteps": 201600}
{"avg_ep_ret": -50.650486274637906, "avg_ep_len": 999.0, "timesteps": 206400}
{"avg_ep_ret": -49.79355368445606, "avg_ep_len": 999.0, "timesteps": 211200}
{"avg_ep_ret": -50.06768326206259, "avg_ep_len": 999.0, "timesteps": 216000}
{"avg_ep_ret": -50.08997017811208, "avg_ep_len": 999.0, "timesteps": 220800}
{"avg_ep_ret": -26.280314751054107, "avg_ep_len": 996.5, "timesteps": 225600}
{"avg_ep_ret": -50.75007038584132, "avg_ep_len": 999.0, "timesteps": 230400}
{"avg_ep_ret": -50.003817084217545, "avg_ep_len": 999.0, "timesteps": 235200}
{"avg_ep_ret": -50.63927136448059, "avg_ep_len": 999.0, "timesteps": 240000}
{"avg_ep_ret": -50.054790668163264, "avg_ep_len": 999.0, "timesteps": 244800}
{"avg_ep_ret": -50.716660633649454, "avg_ep_len": 999.0, "timesteps": 249600}
{"avg_ep_ret": -51.166090078316856, "avg_ep_len": 999.0, "timesteps": 254400}
{"avg_ep_ret": -50.35025395125287, "avg_ep_len": 999.0, "timesteps": 259200}
{"avg_ep_ret": -27.64694219857119, "avg_ep_len": 922.8, "timesteps": 264000}
{"avg_ep_ret": -51.045694581489315, "avg_ep_len": 999.0, "timesteps": 268800}
{"avg_ep_ret": -50.476483109663796, "avg_ep_len": 999.0, "timesteps": 273600}
{"avg_ep_ret": -49.90613966284394, "avg_ep_len": 999.0, "timesteps": 278400}
{"avg_ep_ret": -49.82142992672994, "avg_ep_len": 999.0, "timesteps": 283200}
{"avg_ep_ret": -50.47062538800165, "avg_ep_len": 999.0, "timesteps": 288000}
{"avg_ep_ret": -50.03560007690217, "avg_ep_len": 999.0, "timesteps": 292800}
{"avg_ep_ret": -50.16409448539328, "avg_ep_len": 999.0, "timesteps": 297600}
{"avg_ep_ret": -50.55278018401036, "avg_ep_len": 999.0, "timesteps": 302400}
{"avg_ep_ret": -50.677188707899596, "avg_ep_len": 999.0, "timesteps": 307200}
{"avg_ep_ret": -50.01164288872837, "avg_ep_len": 999.0, "timesteps": 312000}
{"avg_ep_ret": -50.550547223615055, "avg_ep_len": 999.0, "timesteps": 316800}
{"avg_ep_ret": -49.42145146478549, "avg_ep_len": 999.0, "timesteps": 321600}
{"avg_ep_ret": -50.08543773313184, "avg_ep_len": 999.0, "timesteps": 326400}
{"avg_ep_ret": -50.396540694563875, "avg_ep_len": 999.0, "timesteps": 331200}
{"avg_ep_ret": -50.66781122624018, "avg_ep_len": 999.0, "timesteps": 336000}
{"avg_ep_ret": -49.7608451013726, "avg_ep_len": 999.0, "timesteps": 340800}
{"avg_ep_ret": -50.76578913184754, "avg_ep_len": 999.0, "timesteps": 345600}
{"avg_ep_ret": -49.992940826028274, "avg_ep_len": 999.0, "timesteps": 350400}
{"avg_ep_ret": -49.49602035677259, "avg_ep_len": 999.0, "timesteps": 355200}
{"avg_ep_ret": -50.800338457695204, "avg_ep_len": 999.0, "timesteps": 360000}
{"avg_ep_ret": -50.35923430961758, "avg_ep_len": 999.0, "timesteps": 364800}
{"avg_ep_ret": -49.83607759653927, "avg_ep_len": 999.0, "timesteps": 369600}
{"avg_ep_ret": -50.466054148684954, "avg_ep_len": 999.0, "timesteps": 374400}
{"avg_ep_ret": -49.31870917208421, "avg_ep_len": 999.0, "timesteps": 379200}
{"avg_ep_ret": -50.36913166811148, "avg_ep_len": 999.0, "timesteps": 384000}
{"avg_ep_ret": -51.049355696224865, "avg_ep_len": 999.0, "timesteps": 388800}
{"avg_ep_ret": -50.110957198799234, "avg_ep_len": 999.0, "timesteps": 393600}
{"avg_ep_ret": -50.477946797550615, "avg_ep_len": 999.0, "timesteps": 398400}
{"avg_ep_ret": -50.68639755420328, "avg_ep_len": 999.0, "timesteps": 403200}
{"avg_ep_ret": -50.49476265355837, "avg_ep_len": 999.0, "timesteps": 408000}
{"avg_ep_ret": -50.523190351771675, "avg_ep_len": 999.0, "timesteps": 412800}
{"avg_ep_ret": -49.79317151800819, "avg_ep_len": 999.0, "timesteps": 417600}
{"avg_ep_ret": -50.6970247975811, "avg_ep_len": 999.0, "timesteps": 422400}
{"avg_ep_ret": -50.89008124675027, "avg_ep_len": 999.0, "timesteps": 427200}
{"avg_ep_ret": -49.399627907698815, "avg_ep_len": 999.0, "timesteps": 432000}
{"avg_ep_ret": -50.412539233879556, "avg_ep_len": 999.0, "timesteps": 436800}
{"avg_ep_ret": -50.99244641488292, "avg_ep_len": 999.0, "timesteps": 441600}
{"avg_ep_ret": -50.12200732137925, "avg_ep_len": 999.0, "timesteps": 446400}
{"avg_ep_ret": -50.541743766949814, "avg_ep_len": 999.0, "timesteps": 451200}
{"avg_ep_ret": -49.67957121071378, "avg_ep_len": 999.0, "timesteps": 456000}
{"avg_ep_ret": -50.446397998636854, "avg_ep_len": 999.0, "timesteps": 460800}
{"avg_ep_ret": -50.24462390725247, "avg_ep_len": 999.0, "timesteps": 465600}
{"avg_ep_ret": -50.01852172077922, "avg_ep_len": 999.0, "timesteps": 470400}
{"avg_ep_ret": -49.93937130333019, "avg_ep_len": 999.0, "timesteps": 475200}
{"avg_ep_ret": -51.455703925646795, "avg_ep_len": 999.0, "timesteps": 480000}
{"avg_ep_ret": -50.65694722279645, "avg_ep_len": 999.0, "timesteps": 484800}
{"avg_ep_ret": -50.49572166784005, "avg_ep_len": 999.0, "timesteps": 489600}
{"avg_ep_ret": -50.264692529005416, "avg_ep_len": 999.0, "timesteps": 494400}
{"avg_ep_ret": -49.89185129953467, "avg_ep_len": 999.0, "timesteps": 499200}
{"avg_ep_ret": -51.3406857567597, "avg_ep_len": 999.0, "timesteps": 504000}
{"avg_ep_ret": -50.696680928117495, "avg_ep_len": 999.0, "timesteps": 508800}
{"avg_ep_ret": -50.03552620842146, "avg_ep_len": 999.0, "timesteps": 513600}
{"avg_ep_ret": -50.367836416177326, "avg_ep_len": 999.0, "timesteps": 518400}
{"avg_ep_ret": -50.21391189112527, "avg_ep_len": 999.0, "timesteps": 523200}
{"avg_ep_ret": -50.72727691868347, "avg_ep_len": 999.0, "timesteps": 528000}
{"avg_ep_ret": -50.53729158472738, "avg_ep_len": 999.0, "timesteps": 532800}
{"avg_ep_ret": -51.09643867383697, "avg_ep_len": 999.0, "timesteps": 537600}
{"avg_ep_ret": -50.18232662261865, "avg_ep_len": 999.0, "timesteps": 542400}
{"avg_ep_ret": -49.55044409714106, "avg_ep_len": 999.0, "timesteps": 547200}
{"avg_ep_ret": -49.683415446086535, "avg_ep_len": 999.0, "timesteps": 552000}
{"avg_ep_ret": -50.26900681432894, "avg_ep_len": 999.0, "timesteps": 556800}
{"avg_ep_ret": -50.021398192209986, "avg_ep_len": 999.0, "timesteps": 561600}
{"avg_ep_ret": -50.25242661436769, "avg_ep_len": 999.0, "timesteps": 566400}
{"avg_ep_ret": -50.72838938139083, "avg_ep_len": 999.0, "timesteps": 571200}
{"avg_ep_ret": -51.03136591977979, "avg_ep_len": 999.0, "timesteps": 576000}
{"avg_ep_ret": -50.9283262528048, "avg_ep_len": 999.0, "timesteps": 580800}
{"avg_ep_ret": -49.52264837610778, "avg_ep_len": 999.0, "timesteps": 585600}
{"avg_ep_ret": -50.71100182952064, "avg_ep_len": 999.0, "timesteps": 590400}
{"avg_ep_ret": -50.6551949142865, "avg_ep_len": 999.0, "timesteps": 595200}
{"avg_ep_ret": -49.689090749322006, "avg_ep_len": 999.0, "timesteps": 600000}
{"avg_ep_ret": -49.86799203495825, "avg_ep_len": 999.0, "timesteps": 604800}
{"avg_ep_ret": -50.94172651228157, "avg_ep_len": 999.0, "timesteps": 609600}
{"avg_ep_ret": -49.92762816133652, "avg_ep_len": 999.0, "timesteps": 614400}
{"avg_ep_ret": -50.17913520782609, "avg_ep_len": 999.0, "timesteps": 619200}
{"avg_ep_ret": -49.84388618951672, "avg_ep_len": 999.0, "timesteps": 624000}
{"avg_ep_ret": -49.94856117095391, "avg_ep_len": 999.0, "timesteps": 628800}
{"avg_ep_ret": -50.65133992506329, "avg_ep_len": 999.0, "timesteps": 633600}
{"avg_ep_ret": -49.46522841029853, "avg_ep_len": 999.0, "timesteps": 638400}
{"avg_ep_ret": -50.06783679859364, "avg_ep_len": 999.0, "timesteps": 643200}
{"avg_ep_ret": -50.2787626390858, "avg_ep_len": 999.0, "timesteps": 648000}
{"avg_ep_ret": -49.74255824536458, "avg_ep_len": 999.0, "timesteps": 652800}
{"avg_ep_ret": -50.73652036158979, "avg_ep_len": 999.0, "timesteps": 657600}
{"avg_ep_ret": -50.91392176255223, "avg_ep_len": 999.0, "timesteps": 662400}
{"avg_ep_ret": -50.44225005162312, "avg_ep_len": 999.0, "timesteps": 667200}
{"avg_ep_ret": -50.42671725065934, "avg_ep_len": 999.0, "timesteps": 672000}
{"avg_ep_ret": -49.81517139901479, "avg_ep_len": 999.0, "timesteps": 676800}
{"avg_ep_ret": -50.22920425277955, "avg_ep_len": 999.0, "timesteps": 681600}
{"avg_ep_ret": -50.010770584923065, "avg_ep_len": 999.0, "timesteps": 686400}
{"avg_ep_ret": -49.39206029833184, "avg_ep_len": 999.0, "timesteps": 691200}
{"avg_ep_ret": -50.06630698956215, "avg_ep_len": 999.0, "timesteps": 696000}
{"avg_ep_ret": -50.258249265382446, "avg_ep_len": 999.0, "timesteps": 700800}
{"avg_ep_ret": -50.38667246488219, "avg_ep_len": 999.0, "timesteps": 705600}
{"avg_ep_ret": -50.62510824795771, "avg_ep_len": 999.0, "timesteps": 710400}
{"avg_ep_ret": -49.98440546706043, "avg_ep_len": 999.0, "timesteps": 715200}
{"avg_ep_ret": -50.00991186040755, "avg_ep_len": 999.0, "timesteps": 720000}
{"avg_ep_ret": -50.446157516410715, "avg_ep_len": 999.0, "timesteps": 724800}
{"avg_ep_ret": -50.84374189366784, "avg_ep_len": 999.0, "timesteps": 729600}
{"avg_ep_ret": -50.7384207631239, "avg_ep_len": 999.0, "timesteps": 734400}
{"avg_ep_ret": -49.53331494034253, "avg_ep_len": 999.0, "timesteps": 739200}
{"avg_ep_ret": -51.23682018213533, "avg_ep_len": 999.0, "timesteps": 744000}
{"avg_ep_ret": -50.34911123560735, "avg_ep_len": 999.0, "timesteps": 748800}
{"avg_ep_ret": -50.310298737042096, "avg_ep_len": 999.0, "timesteps": 753600}
{"avg_ep_ret": -50.19466821229255, "avg_ep_len": 999.0, "timesteps": 758400}
{"avg_ep_ret": -50.33440656841886, "avg_ep_len": 999.0, "timesteps": 763200}
{"avg_ep_ret": -50.064390672243896, "avg_ep_len": 999.0, "timesteps": 768000}
{"avg_ep_ret": -50.700210063660236, "avg_ep_len": 999.0, "timesteps": 772800}
{"avg_ep_ret": -49.9503509189197, "avg_ep_len": 999.0, "timesteps": 777600}
{"avg_ep_ret": -50.620624459038325, "avg_ep_len": 999.0, "timesteps": 782400}
{"avg_ep_ret": -50.09198746051717, "avg_ep_len": 999.0, "timesteps": 787200}
{"avg_ep_ret": -49.72534861718116, "avg_ep_len": 999.0, "timesteps": 792000}
{"avg_ep_ret": -50.68748743960329, "avg_ep_len": 999.0, "timesteps": 796800}
{"avg_ep_ret": -50.61525510635377, "avg_ep_len": 999.0, "timesteps": 801600}
{"avg_ep_ret": -50.30762595686666, "avg_ep_len": 999.0, "timesteps": 806400}
{"avg_ep_ret": -50.97444172791744, "avg_ep_len": 999.0, "timesteps": 811200}
{"avg_ep_ret": -50.53814455017831, "avg_ep_len": 999.0, "timesteps": 816000}
{"avg_ep_ret": -50.29014387454468, "avg_ep_len": 999.0, "timesteps": 820800}
{"avg_ep_ret": -50.51012149165962, "avg_ep_len": 999.0, "timesteps": 825600}
{"avg_ep_ret": -50.0052668295926, "avg_ep_len": 999.0, "timesteps": 830400}
{"avg_ep_ret": -50.359002380939025, "avg_ep_len": 999.0, "timesteps": 835200}
{"avg_ep_ret": -50.51787465181987, "avg_ep_len": 999.0, "timesteps": 840000}
{"avg_ep_ret": -50.811020161235504, "avg_ep_len": 999.0, "timesteps": 844800}
{"avg_ep_ret": -50.16509802074098, "avg_ep_len": 999.0, "timesteps": 849600}
{"avg_ep_ret": -50.273525582736106, "avg_ep_len": 999.0, "timesteps": 854400}
{"avg_ep_ret": -50.5742926180255, "avg_ep_len": 999.0, "timesteps": 859200}
{"avg_ep_ret": -50.08944781369936, "avg_ep_len": 999.0, "timesteps": 864000}
{"avg_ep_ret": -50.96910718060983, "avg_ep_len": 999.0, "timesteps": 868800}
{"avg_ep_ret": -49.82582163355247, "avg_ep_len": 999.0, "timesteps": 873600}
{"avg_ep_ret": -50.63714020141296, "avg_ep_len": 999.0, "timesteps": 878400}
{"avg_ep_ret": -51.2028109964991, "avg_ep_len": 999.0, "timesteps": 883200}
{"avg_ep_ret": -50.25270020809734, "avg_ep_len": 999.0, "timesteps": 888000}
{"avg_ep_ret": -50.28696201212453, "avg_ep_len": 999.0, "timesteps": 892800}
{"avg_ep_ret": -50.81384115373857, "avg_ep_len": 999.0, "timesteps": 897600}
{"avg_ep_ret": -51.03370164540697, "avg_ep_len": 999.0, "timesteps": 902400}
{"avg_ep_ret": -50.8237377789694, "avg_ep_len": 999.0, "timesteps": 907200}
{"avg_ep_ret": -50.018069020865994, "avg_ep_len": 999.0, "timesteps": 912000}
{"avg_ep_ret": -49.935612906908624, "avg_ep_len": 999.0, "timesteps": 916800}
{"avg_ep_ret": -49.983976807758836, "avg_ep_len": 999.0, "timesteps": 921600}
{"avg_ep_ret": -49.7088053254176, "avg_ep_len": 999.0, "timesteps": 926400}
{"avg_ep_ret": -49.80800039031447, "avg_ep_len": 999.0, "timesteps": 931200}
{"avg_ep_ret": -50.34283712134218, "avg_ep_len": 999.0, "timesteps": 936000}
{"avg_ep_ret": -49.99018588231445, "avg_ep_len": 999.0, "timesteps": 940800}
{"avg_ep_ret": -49.728307990060294, "avg_ep_len": 999.0, "timesteps": 945600}
{"avg_ep_ret": -50.422987240153745, "avg_ep_len": 999.0, "timesteps": 950400}
{"avg_ep_ret": -50.6216414591219, "avg_ep_len": 999.0, "timesteps": 955200}
{"avg_ep_ret": -50.32676877686985, "avg_ep_len": 999.0, "timesteps": 960000}
{"avg_ep_ret": -50.20565696645774, "avg_ep_len": 999.0, "timesteps": 964800}
{"avg_ep_ret": -50.372988786818794, "avg_ep_len": 999.0, "timesteps": 969600}
{"avg_ep_ret": -50.07223093926764, "avg_ep_len": 999.0, "timesteps": 974400}
{"avg_ep_ret": -49.96861034318098, "avg_ep_len": 999.0, "timesteps": 979200}
{"avg_ep_ret": -49.89639995719724, "avg_ep_len": 999.0, "timesteps": 984000}
{"avg_ep_ret": -50.10293192394913, "avg_ep_len": 999.0, "timesteps": 988800}
{"avg_ep_ret": -49.924229190457666, "avg_ep_len": 999.0, "timesteps": 993600}
{"avg_ep_ret": -50.517937174829115, "avg_ep_len": 999.0, "timesteps": 998400}
